frtzbxrdr/__init__.py
frtzbxrdr/auth.py
frtzbxrdr/frtzbxrdr.py
frtzbxrdr/monitor.py
frtzbxrdr-0.0.2.dist-info/LICENSE.txt
frtzbxrdr-0.0.2.dist-info/METADATA
frtzbxrdr-0.0.2.dist-info/WHEEL
frtzbxrdr-0.0.2.dist-info/entry_points.txt
frtzbxrdr-0.0.2.dist-info/top_level.txt
frtzbxrdr-0.0.2.dist-info/RECORD
