Metadata-Version: 2.1
Name: frtzbxrdr
Version: 0.0.2
Summary: Check your fritzbox to see who comes and goes in your WiFi network
Home-page: https://github.com/DaEwe/frtzboxrdr
Author: Daniel Ewert
Author-email: ewert.daniel@gmail.com
License: Unlicense
Platform: any
Classifier: Development Status :: 4 - Beta
Classifier: Programming Language :: Python
Requires-Python: >=3.8
License-File: LICENSE.txt
Requires-Dist: schedule
Requires-Dist: requests
Requires-Dist: importlib-metadata ; python_version < "3.8"
Provides-Extra: testing
Requires-Dist: setuptools ; extra == 'testing'
Requires-Dist: pytest ; extra == 'testing'
Requires-Dist: pytest-cov ; extra == 'testing'
